tracebackturbo/__init__.py
tracebackturbo/tracebackturbo.py
tracebackturbo3-0.3.dist-info/METADATA
tracebackturbo3-0.3.dist-info/RECORD
tracebackturbo3-0.3.dist-info/WHEEL
tracebackturbo3-0.3.dist-info/top_level.txt
