Metadata-Version: 2.1
Name: tracebackturbo3
Version: 0.3
Summary: Patched version of traceback, also dumps local and global scope vars.
Home-page: https://github.com/cxcv/python-tracebackturbo3
Maintainer: Benjamin Schweizer
Maintainer-email: cxcv@cxcv.de
License: PSF
Platform: UNKNOWN
Classifier: Intended Audience :: Developers
Classifier: License :: OSI Approved :: Python Software Foundation License
Classifier: Programming Language :: Python
Classifier: Programming Language :: Python :: 3
Classifier: Topic :: Software Development :: Libraries :: Python Modules
